vterminal/__init__.py
vterminal-1.3.21.dist-info/LICENSE.txt
vterminal-1.3.21.dist-info/METADATA
vterminal-1.3.21.dist-info/WHEEL
vterminal-1.3.21.dist-info/top_level.txt
vterminal-1.3.21.dist-info/RECORD
