Metadata-Version: 2.1
Name: vterminal
Version: 1.3.21
Summary: A terminal emulator using pygame.
Home-page: https://github.com/mutater/vterminal
Author: Vincent Glendenning
Author-email: vincentglendenning@gmail.com
License: UNKNOWN
Platform: UNKNOWN
Classifier: Programming Language :: Python :: 3
Classifier: License :: OSI Approved :: MIT License
Classifier: Operating System :: OS Independent
Requires-Python: >=3.6
